mundane/__init__.py
mundane/_any_money.py
mundane/_currencies.py
mundane/_currency.py
mundane/_money.py
mundane/_typed_money.py
mundane/_typed_money_mixin.py
mundane/py.typed
mundane-0.1.1.dist-info/METADATA
mundane-0.1.1.dist-info/WHEEL
mundane-0.1.1.dist-info/licenses/LICENSE.txt
mundane-0.1.1.dist-info/RECORD
