Metadata-Version: 2.3
Name: mundane
Version: 0.1.1
Summary: Pythonic Money class. Correct. Type-safe. Matches expectations.
Project-URL: Repository, https://github.com/LEW21/python-mundane
Author-email: Linus Lewandowski <linus@lew21.net>
License-Expression: MIT
License-File: LICENSE.txt
Classifier: Development Status :: 4 - Beta
Classifier: License :: OSI Approved :: MIT License
Classifier: Operating System :: OS Independent
Classifier: Programming Language :: Python
Classifier: Programming Language :: Python :: 3.12
Classifier: Programming Language :: Python :: Implementation :: CPython
Classifier: Topic :: Office/Business :: Financial
Classifier: Typing :: Typed
Requires-Python: >=3.12
